galstreams/__init__.py
galstreams/config.py
galstreams/footprint.py
galstreams/random.py
galstreams/lib/globular_cluster_params.harris2010.tableI.csv
galstreams/lib/master_log.comments.txt
galstreams/lib/master_log.discovery_refs.txt
galstreams/lib/master_log.txt
galstreams/tracks/track.ep.Acheron.grillmair2009.ecsv
galstreams/tracks/track.ep.Acheron.grillmair2009.summary.ecsv
galstreams/tracks/track.ep.Cocytos.grillmair2009.ecsv
galstreams/tracks/track.ep.Cocytos.grillmair2009.summary.ecsv
galstreams/tracks/track.ep.Gaia-3.malhan2018.ecsv
galstreams/tracks/track.ep.Gaia-3.malhan2018.summary.ecsv
galstreams/tracks/track.ep.Gaia-4.malhan2018.ecsv
galstreams/tracks/track.ep.Gaia-4.malhan2018.summary.ecsv
galstreams/tracks/track.ep.Gaia-5.malhan2018.ecsv
galstreams/tracks/track.ep.Gaia-5.malhan2018.summary.ecsv
galstreams/tracks/track.ep.Jet.jethwa2018.ecsv
galstreams/tracks/track.ep.Jet.jethwa2018.summary.ecsv
galstreams/tracks/track.ep.Lethe.grillmair2009.ecsv
galstreams/tracks/track.ep.Lethe.grillmair2009.summary.ecsv
galstreams/tracks/track.ep.Pal13.shipp2020.ecsv
galstreams/tracks/track.ep.Pal13.shipp2020.summary.ecsv
galstreams/tracks/track.ep.Palca.shipp2018.ecsv
galstreams/tracks/track.ep.Palca.shipp2018.summary.ecsv
galstreams/tracks/track.ep.Ravi.shipp2018.ecsv
galstreams/tracks/track.ep.Ravi.shipp2018.summary.ecsv
galstreams/tracks/track.ep.Styx.grillmair2009.ecsv
galstreams/tracks/track.ep.Styx.grillmair2009.summary.ecsv
galstreams/tracks/track.ep.Turbio.shipp2018.ecsv
galstreams/tracks/track.ep.Turbio.shipp2018.summary.ecsv
galstreams/tracks/track.ep.Wambelong.shipp2018.ecsv
galstreams/tracks/track.ep.Wambelong.shipp2018.summary.ecsv
galstreams/tracks/track.ep.Willka_Yaku.shipp2018.ecsv
galstreams/tracks/track.ep.Willka_Yaku.shipp2018.summary.ecsv
galstreams/tracks/track.po.20.0-1.mateu2018.ecsv
galstreams/tracks/track.po.20.0-1.mateu2018.summary.ecsv
galstreams/tracks/track.po.Corvus.mateu2018.ecsv
galstreams/tracks/track.po.Corvus.mateu2018.summary.ecsv
galstreams-1.0.3.dist-info/AUTHORS
galstreams-1.0.3.dist-info/LICENSE
galstreams-1.0.3.dist-info/METADATA
galstreams-1.0.3.dist-info/WHEEL
galstreams-1.0.3.dist-info/top_level.txt
galstreams-1.0.3.dist-info/RECORD
