Metadata-Version: 2.1
Name: galstreams
Version: 1.0.3
Summary: MW stream library toolkit
Home-page: https://github.com/cmateu/galstreams
Author: C. Mateu
Author-email: cmateu@fisica.edu.uy
License: BSD-3-Clause
Platform: UNKNOWN
Classifier: Programming Language :: Python :: 3
Classifier: Development Status :: 5 - Production/Stable
Classifier: Programming Language :: Python :: 3.5
Classifier: Topic :: Scientific/Engineering :: Astronomy
Requires-Python: >=3.5
License-File: LICENSE
License-File: AUTHORS
Requires-Dist: numpy
Requires-Dist: scipy
Requires-Dist: astropy
